
   [
        {
            "title": "Bastareaud left out of 31-man France squad to prepare for World Cup",
            "selfLink": "bastareaud-left-out-of-31-man-france-squad-to-prepare-for-world-cup",
            "description": "Mathieu Bastareaud has been left out of a 31-man France squad to prepare for the World Cup.",
            "body": [
                {
                    "data": {},
                    "content": [
                        {
                            "data": {},
                            "marks": [],
                            "value": "Mathieu Bastareaud has been left out of a 31-man France squad to prepare for the World Cup.",
                            "nodeType": "text"
                        }
                    ],
                    "nodeType": "paragraph"
                },
                {
                    "data": {},
                    "content": [
                        {
                            "data": {},
                            "marks": [],
                            "value": "The powerful Toulon centre, who has captained Les Bleus three times during his 54-cap career, missed out in a group announced by France head coach Jacques Brunel.",
                            "nodeType": "text"
                        }
                    ],
                    "nodeType": "paragraph"
                },
                {
                    "data": {},
                    "content": [
                        {
                            "data": {},
                            "marks": [],
                            "value": "The squad, together with six named reserves, will work towards the tournament in Japan before a final squad is confirmed on September 2.",
                            "nodeType": "text"
                        }
                    ],
                    "nodeType": "paragraph"
                },
                {
                    "data": {},
                    "content": [
                        {
                            "data": {},
                            "marks": [],
                            "value": "Bastareaud, 30, will move to Major League Rugby in America later this year, joining Rugby United New York.",
                            "nodeType": "text"
                        }
                    ],
                    "nodeType": "paragraph"
                },
                {
                    "data": {},
                    "content": [
                        {
                            "data": {},
                            "marks": [],
                            "value": "Toulouse centre Sofiane Guitoune looks set to prosper from Bastareaud's absence, while Brunel has included uncapped players in Guitoune's club colleague Peato Mauvaka, and Toulon prop Emerick Setiano.",
                            "nodeType": "text"
                        }
                    ],
                    "nodeType": "paragraph"
                },
                {
                    "data": {},
                    "content": [
                        {
                            "data": {},
                            "marks": [],
                            "value": "Bastareaud apart, other notable absentees include wing Teddy Thomas, scrum-half Morgan Parra and prop Uini Atonio.",
                            "nodeType": "text"
                        }
                    ],
                    "nodeType": "paragraph"
                },
                {
                    "data": {},
                    "content": [
                        {
                            "data": {},
                            "marks": [],
                            "value": "\"We have followed (Sofiane) Guitoune all year,\" Brunel told L'Equipe. \"He performed very well.",
                            "nodeType": "text"
                        }
                    ],
                    "nodeType": "paragraph"
                },
                {
                    "data": {},
                    "content": [
                        {
                            "data": {},
                            "marks": [],
                            "value": "\"We did not know if he would produce the (form). He did it all year long.",
                            "nodeType": "text"
                        }
                    ],
                    "nodeType": "paragraph"
                },
                {
                    "data": {},
                    "content": [
                        {
                            "data": {},
                            "marks": [],
                            "value": "\"The group is rejuvenated with many players who are 25 years and under, but there are still players with experience with (Yoann) Huget, (Wesley) Fofana and (Maxime) Medard.\"",
                            "nodeType": "text"
                        }
                    ],
                    "nodeType": "paragraph"
                },
                {
                    "data": {},
                    "content": [
                        {
                            "data": {},
                            "marks": [],
                            "value": "France are in the same World Cup pool as England, Argentina, the United States and Tonga. Their opening game is against Argentina in Tokyo on September 21.",
                            "nodeType": "text"
                        }
                    ],
                    "nodeType": "paragraph"
                },
                {
                    "data": {},
                    "content": [
                        {
                            "data": {},
                            "marks": [],
                            "value": "Squad: G Alldritt (La Rochelle), D Bamba (Brive), Y Camara (Montpellier), C Chat (Racing 92), G Doumayrou (La Rochelle), A Dupont (Toulouse), G Fickou (Stade Francais), W Fofana (Clermont Auvergne), P Gabrillagues (Stade Francais), G Guirado (Toulon), S Guitoune (Toulouse), Y Huget (Toulouse), A Uturria (Clermont Auvergne), F Lambey (Lyon), W Lauret (Racing 92), B Le Roux (Racing 92), C Lopez (Clermont Auvergne), M Machenaud (Racing 92), P Mauvaka (Toulouse), M Medard (Toulouse), R Ntamack (Toulouse), D Penaud (Clermont Auvergne), L Picamoles (Montpellier), J Poirot (Bordeax-Begles), D Priso (La Rochelle), A Raka (Clermont Auvergne), T Ramos (Toulouse), B Serin (Bordeaux-Begles), E Setiano (Toulon), R Slimani (Clermont Auvergne), S Vahaamahina (Clermont Auvergne).",
                            "nodeType": "text"
                        }
                    ],
                    "nodeType": "paragraph"
                },
                {
                    "data": {},
                    "content": [
                        {
                            "data": {},
                            "marks": [],
                            "value": "Reserves: A Belleau (Toulon), F Cros (Toulouse), E Falgoux (Clermont Auvergne), C Ollivon (Toulon), V Rattez (La Rochelle), P Willemse (Montpellier).",
                            "nodeType": "text"
                        }
                    ],
                    "nodeType": "paragraph"
                }
            ],
            "images": [
                {
                    "title": "Mathieu Bastareaud on field for France ",
                    "file": {
                        "url": "//images.ctfassets.net/j2hzbokj7ol2/2kfpaZgH6LR3DTOyjfWW8v/afe50d48cb6383c3599745df592949e6/Mathieu-Bastareaud-france-ingame-profile-portrait.png",
                        "details": {
                            "size": 651758,
                            "image": {
                                "width": 2044,
                                "height": 1468
                            }
                        },
                        "fileName": "Mathieu-Bastareaud-france-ingame-profile-portrait.png",
                        "contentType": "image/png"
                    }
                }
            ],
            "tags": [
                "france",
                "Mathieu Bastareaud"
            ]
        },
        {
            "title": "England face waiting game on Nowell following surgery",
            "selfLink": "england-face-waiting-game-on-nowell-following-surgery",
            "description": "England face a World Cup waiting game on Exeter back Jack Nowell after he underwent ankle surgery.",
            "body": [
                {
                    "data": {},
                    "content": [
                        {
                            "data": {},
                            "marks": [],
                            "value": "England face a World Cup waiting game on Exeter back Jack Nowell after he underwent ankle surgery.",
                            "nodeType": "text"
                        }
                    ],
                    "nodeType": "paragraph"
                },
                {
                    "data": {},
                    "content": [
                        {
                            "data": {},
                            "marks": [],
                            "value": "Exeter rugby director Rob Baxter confirmed that the operation was successful, and said \"at this stage we see no reason\" why Nowell's World Cup hopes should be jeopardised.",
                            "nodeType": "text"
                        }
                    ],
                    "nodeType": "paragraph"
                },
                {
                    "data": {},
                    "content": [
                        {
                            "data": {},
                            "marks": [],
                            "value": "England's opening World Cup warm-up fixture is against Wales on August 11, and their first tournament match is an appointment with Tonga in Sapporo six weeks later.",
                            "nodeType": "text"
                        }
                    ],
                    "nodeType": "paragraph"
                },
                {
                    "data": {},
                    "content": [
                        {
                            "data": {},
                            "marks": [],
                            "value": "Press Association Sport understands that Nowell, who has scored 13 tries in 33 appearances for England, could be fit again by mid to late August.",
                            "nodeType": "text"
                        }
                    ],
                    "nodeType": "paragraph"
                },
                {
                    "data": {},
                    "content": [
                        {
                            "data": {},
                            "marks": [],
                            "value": "Nowell, an important part of England boss Eddie Jones' World Cup plans, was injured in the Gallagher Premiership final against Saracens earlier this month.",
                            "nodeType": "text"
                        }
                    ],
                    "nodeType": "paragraph"
                },
                {
                    "data": {},
                    "content": [
                        {
                            "data": {},
                            "marks": [],
                            "value": "The 26-year-old, who had an outstanding game at Twickenham despite Exeter's defeat, went off midway through the second half after attempting to tackle Saracens wing Sean Maitland.",
                            "nodeType": "text"
                        }
                    ],
                    "nodeType": "paragraph"
                },
                {
                    "data": {},
                    "content": [
                        {
                            "data": {},
                            "marks": [],
                            "value": "In a statement, Exeter said: \"Nowell underwent initial scans on both his knee and ankle in the aftermath of the final.",
                            "nodeType": "text"
                        }
                    ],
                    "nodeType": "paragraph"
                },
                {
                    "data": {},
                    "content": [
                        {
                            "data": {},
                            "marks": [],
                            "value": "\"Since then, the Cornishman has been away on holiday with his family, after which he has returned to Exeter and underwent surgery on his ankle on Tuesday.\"",
                            "nodeType": "text"
                        }
                    ],
                    "nodeType": "paragraph"
                },
                {
                    "data": {},
                    "content": [
                        {
                            "data": {},
                            "marks": [],
                            "value": "Baxter has not put a timescale on when he expects Nowell to be fully fit again, but offered a positive outlook.",
                            "nodeType": "text"
                        }
                    ],
                    "nodeType": "paragraph"
                },
                {
                    "data": {},
                    "content": [
                        {
                            "data": {},
                            "marks": [],
                            "value": "\"Jack's had an operation on his ankle,\" Baxter said.",
                            "nodeType": "text"
                        }
                    ],
                    "nodeType": "paragraph"
                },
                {
                    "data": {},
                    "content": [
                        {
                            "data": {},
                            "marks": [],
                            "value": "\"And at this stage we see no reason why it should jeopardise him being involved with England at the Rugby World Cup, nor with us heading into the new season.\"",
                            "nodeType": "text"
                        }
                    ],
                    "nodeType": "paragraph"
                }
            ],
            "images": [
                {
                    "title": "Jack Nowell on-field for Exeter",
                    "file": {
                        "url": "//images.ctfassets.net/j2hzbokj7ol2/34hODn20XpCm4SozASJzIo/12b6c46dd4fd5ec18725dab81586d78a/jack-nowell-exeter-portrait.png",
                        "details": {
                            "size": 481037,
                            "image": {
                                "width": 1548,
                                "height": 1272
                            }
                        },
                        "fileName": "jack-nowell-exeter-portrait.png",
                        "contentType": "image/png"
                    }
                }
            ],
            "tags": [
                "Jack Nowell",
                "Exeter",
                "England"
            ]
        },
        {
            "title": "Gatland to coach Barbarians against Wales in first match after stepping down",
            "selfLink": "gatland-to-coach-barbarians-against-wales-in-first-match-after-stepping-down",
            "description": "Warren Gatland's first match after stepping down as Wales boss this autumn will be against the team he has guided for the past 12 years.",
            "body": [
                {
                    "data": {},
                    "content": [
                        {
                            "data": {},
                            "marks": [],
                            "value": "Warren Gatland's first match after stepping down as Wales boss this autumn will be against the team he has guided for the past 12 years.",
                            "nodeType": "text"
                        }
                    ],
                    "nodeType": "paragraph"
                },
                {
                    "data": {},
                    "content": [
                        {
                            "data": {},
                            "marks": [],
                            "value": "Gatland, who leaves his post after the World Cup, has been appointed Barbarians coach for a fixture against Wales in Cardiff on November 30.",
                            "nodeType": "text"
                        }
                    ],
                    "nodeType": "paragraph"
                },
                {
                    "data": {},
                    "content": [
                        {
                            "data": {},
                            "marks": [],
                            "value": "The first meeting between the sides since 2012 will be Wayne Pivac's debut as Gatland's successor.",
                            "nodeType": "text"
                        }
                    ],
                    "nodeType": "paragraph"
                },
                {
                    "data": {},
                    "content": [
                        {
                            "data": {},
                            "marks": [],
                            "value": "\"It goes without saying that this match has huge significance to me. Wales has been my home for the last 12 years and I have thoroughly enjoyed my time here,\" Gatland said.",
                            "nodeType": "text"
                        }
                    ],
                    "nodeType": "paragraph"
                }
            ],
            "images": [
                {
                    "title": "Warren Gatland",
                    "file": {
                        "url": "//images.ctfassets.net/j2hzbokj7ol2/7LyxyGjbWZ4dlsmWpf0Cgt/367e79737b31d0e067443e53b5ba47ef/warren-gatland.jpg",
                        "details": {
                            "size": 24088,
                            "image": {
                                "width": 540,
                                "height": 304
                            }
                        },
                        "fileName": "warren-gatland.jpg",
                        "contentType": "image/jpeg"
                    }
                }
            ],
            "tags": [
                "Warren Gatland"
            ]
        },
        {
            "title": "RFU boss Sweeney rejects idea of planning for Eddie Jones' successor",
            "selfLink": "rfu-boss-sweeney-rejects-idea-of-planning-for-eddie-jones-successor",
            "description": "New chief executive Bill Sweeney has ripped up England's succession planning for life after head coach Eddie Jones.",
            "body": [
                {
                    "data": {},
                    "content": [
                        {
                            "data": {},
                            "marks": [],
                            "value": "New chief executive Bill Sweeney has ripped up England's succession planning for life after head coach Eddie Jones.",
                            "nodeType": "text"
                        }
                    ],
                    "nodeType": "paragraph"
                },
                {
                    "data": {},
                    "content": [
                        {
                            "data": {},
                            "marks": [],
                            "value": "The Rugby Football Union's fourth chief executive in two years has dispensed with England's long-term plans for how to replace their taskmaster Australian boss.",
                            "nodeType": "text"
                        }
                    ],
                    "nodeType": "paragraph"
                },
                {
                    "data": {},
                    "content": [
                        {
                            "data": {},
                            "marks": [],
                            "value": "Previous chief executives Ian Ritchie, Steve Brown and Nigel Melville all wanted England to develop assistant coaches capable of taking overall charge when Jones departs.",
                            "nodeType": "text"
                        }
                    ],
                    "nodeType": "paragraph"
                },
                {
                    "data": {},
                    "content": [
                        {
                            "data": {},
                            "marks": [],
                            "value": "But now former British Olympic Association chief Sweeney has claimed such early planning would prove \"disruptive\", with Jones and now defence coach John Mitchell contracted until 2021.",
                            "nodeType": "text"
                        }
                    ],
                    "nodeType": "paragraph"
                },
                {
                    "data": {},
                    "content": [
                        {
                            "data": {},
                            "marks": [],
                            "value": "\"I haven't had any conversations about coaching the successor for an extended period towards the end of that contract,\" said Sweeney. \"I think that is too far ahead.",
                            "nodeType": "text"
                        }
                    ],
                    "nodeType": "paragraph"
                },
                {
                    "data": {
                        "target": {
                            "sys": {
                                "space": {
                                    "sys": {
                                        "type": "Link",
                                        "linkType": "Space",
                                        "id": "j2hzbokj7ol2"
                                    }
                                },
                                "id": "2Oy8SD0Kxv4fuqSseXiu0r",
                                "type": "Asset",
                                "createdAt": "2019-06-21T15:33:55.508Z",
                                "updatedAt": "2019-06-21T15:33:55.508Z",
                                "environment": {
                                    "sys": {
                                        "id": "dev",
                                        "type": "Link",
                                        "linkType": "Environment"
                                    }
                                },
                                "revision": 1,
                                "locale": "en-GB"
                            },
                            "fields": {
                                "title": "Eddie Jones",
                                "file": {
                                    "url": "//images.ctfassets.net/j2hzbokj7ol2/2Oy8SD0Kxv4fuqSseXiu0r/51450895b6ea4149b96a00d50d0abb55/eddie-jones.jpg",
                                    "details": {
                                        "size": 24430,
                                        "image": {
                                            "width": 540,
                                            "height": 304
                                        }
                                    },
                                    "fileName": "eddie-jones.jpg",
                                    "contentType": "image/jpeg"
                                }
                            }
                        }
                    },
                    "content": [],
                    "nodeType": "embedded-asset-block"
                },
                {
                    "data": {},
                    "content": [
                        {
                            "data": {},
                            "marks": [],
                            "value": "\"The focus is on the World Cup. The next priority is: have we got the right coaching structure in place for the Six Nations immediately following and what have we got in place going through to 2021?",
                            "nodeType": "text"
                        }
                    ],
                    "nodeType": "paragraph"
                },
                {
                    "data": {},
                    "content": [
                        {
                            "data": {},
                            "marks": [],
                            "value": "\"Eddie is absolutely focused doing the best we can possibly do in Japan. He's committed to staying until 2021. I think any other speculation prior to that would be really disruptive to the situation.",
                            "nodeType": "text"
                        }
                    ],
                    "nodeType": "paragraph"
                },
                {
                    "data": {},
                    "content": [
                        {
                            "data": {},
                            "marks": [],
                            "value": "\"We are comfortable with the coaching set-up we've got. He's a tremendous character to work with. He's very demanding, he pushes us to levels and standards I think we need to aspire to as well, so having any speculation out there pre-World cup would be really disruptive.\"",
                            "nodeType": "text"
                        }
                    ],
                    "nodeType": "paragraph"
                },
                {
                    "data": {},
                    "content": [
                        {
                            "data": {},
                            "marks": [],
                            "value": "Jones insisted on the day of his appointment in November 2015 that part of his job would be to develop assistant coaches capable of taking overall charge.",
                            "nodeType": "text"
                        }
                    ],
                    "nodeType": "paragraph"
                },
                {
                    "data": {
                        "target": {
                            "sys": {
                                "space": {
                                    "sys": {
                                        "type": "Link",
                                        "linkType": "Space",
                                        "id": "j2hzbokj7ol2"
                                    }
                                },
                                "id": "6tgYxEB5DWqyy2H7OXr6IH",
                                "type": "Asset",
                                "createdAt": "2019-06-21T15:35:21.116Z",
                                "updatedAt": "2019-06-21T15:35:21.116Z",
                                "environment": {
                                    "sys": {
                                        "id": "dev",
                                        "type": "Link",
                                        "linkType": "Environment"
                                    }
                                },
                                "revision": 1,
                                "locale": "en-GB"
                            },
                            "fields": {
                                "title": "Rugby Executive",
                                "file": {
                                    "url": "//images.ctfassets.net/j2hzbokj7ol2/6tgYxEB5DWqyy2H7OXr6IH/a419ad6f4bb4a3beadad4a1da7b1b524/sween-article-1.jpg",
                                    "details": {
                                        "size": 20135,
                                        "image": {
                                            "width": 540,
                                            "height": 303
                                        }
                                    },
                                    "fileName": "sween-article-1.jpg",
                                    "contentType": "image/jpeg"
                                }
                            }
                        }
                    },
                    "content": [],
                    "nodeType": "embedded-asset-block"
                },
                {
                    "data": {},
                    "content": [
                        {
                            "data": {},
                            "marks": [],
                            "value": "Then-chief executive Ritchie backed that approach, with his replacement Brown reiterating that stance in January 2018, when Jones' contract was extended beyond the 2019 World Cup.",
                            "nodeType": "text"
                        }
                    ],
                    "nodeType": "paragraph"
                },
                {
                    "data": {},
                    "content": [
                        {
                            "data": {},
                            "marks": [],
                            "value": "New RFU boss Sweeney confirmed Mitchell's extended contract on Thursday, which brings the defence specialist in line with head coach Jones.",
                            "nodeType": "text"
                        }
                    ],
                    "nodeType": "paragraph"
                },
                {
                    "data": {},
                    "content": [
                        {
                            "data": {},
                            "marks": [],
                            "value": "Mitchell had been touted as a possible replacement for Jones in the RFU's previous ideas, but Sweeney has rejected all notion of succession planning.",
                            "nodeType": "text"
                        }
                    ],
                    "nodeType": "paragraph"
                },
                {
                    "data": {},
                    "content": [
                        {
                            "data": {},
                            "marks": [],
                            "value": "When asked about the original plans that had Jones' successor in place by 2020, Sweeney said: \"That is not the intention, I haven't heard that.",
                            "nodeType": "text"
                        }
                    ],
                    "nodeType": "paragraph"
                },
                {
                    "data": {},
                    "content": [
                        {
                            "data": {},
                            "marks": [],
                            "value": "\"We have had no conversations around that. Eddie is taking the team to Japan (on the summer tour in 2020).\"",
                            "nodeType": "text"
                        }
                    ],
                    "nodeType": "paragraph"
                },
                {
                    "data": {},
                    "content": [
                        {
                            "data": {},
                            "marks": [],
                            "value": "When asked if the RFU's original plan had therefore changed, Sweeney said: \"I didn't know it existed in the first place.\"",
                            "nodeType": "text"
                        }
                    ],
                    "nodeType": "paragraph"
                },
                {
                    "data": {},
                    "content": [
                        {
                            "data": {},
                            "marks": [],
                            "value": "Sweeney then defended the RFU's new stance on life after Jones, when it was suggested a lack of planning could prove too loose.",
                            "nodeType": "text"
                        }
                    ],
                    "nodeType": "paragraph"
                },
                {
                    "data": {},
                    "content": [
                        {
                            "data": {},
                            "marks": [],
                            "value": "\"I think that's a little unfair, Eddie is contracted to 2021,\" said Sweeney. \"There was speculation that he'd go post-World Cup but he has never indicated that was the case.",
                            "nodeType": "text"
                        }
                    ],
                    "nodeType": "paragraph"
                },
                {
                    "data": {},
                    "content": [
                        {
                            "data": {},
                            "marks": [],
                            "value": "\"One of the first conversations I had was: 'what is the status? What is his view?' He is committed to going through to 2021.",
                            "nodeType": "text"
                        }
                    ],
                    "nodeType": "paragraph"
                },
                {
                    "data": {},
                    "content": [
                        {
                            "data": {},
                            "marks": [],
                            "value": "\"Steve Borthwick is an RFU employee, he's moved from a contract to being an employee, so he is in place.",
                            "nodeType": "text"
                        }
                    ],
                    "nodeType": "paragraph"
                },
                {
                    "data": {},
                    "content": [
                        {
                            "data": {},
                            "marks": [],
                            "value": "\"Eddie had a strong preference to get John (Mitchell) on board again, they work together well, he wanted him there as defence coach. That's now in place as well.",
                            "nodeType": "text"
                        }
                    ],
                    "nodeType": "paragraph"
                },
                {
                    "data": {},
                    "content": [
                        {
                            "data": {},
                            "marks": [],
                            "value": "\"You've got Neal Hatley going away. You've got Scott Wisemantel possibly, probably going away. Eddie's got views on who he'd like to bring in already at that stage.\"",
                            "nodeType": "text"
                        }
                    ],
                    "nodeType": "paragraph"
                }
            ],
            "images": [
                {
                    "title": "Bill Sweeney",
                    "file": {
                        "url": "//images.ctfassets.net/j2hzbokj7ol2/6XYchTJsiHmCg8LVAOMSQ0/2b81d3ac1c8ca2e3a2058aec4bcd549c/bill-sweeney.jpg",
                        "details": {
                            "size": 26696,
                            "image": {
                                "width": 540,
                                "height": 303
                            }
                        },
                        "fileName": "bill-sweeney.jpg",
                        "contentType": "image/jpeg"
                    }
                }
            ],
            "tags": [
                "Bill Sweeney",
                "RFU",
                "Eddie Jones"
            ]
        },
        {
            "title": "Robshaw and Care left out of England training squad",
            "selfLink": "robshaw-and-care-left-out-of-england-training-squad",
            "description": "Senior internationals Chris Robshaw and Danny Care have been left out of England's first World Cup training squad.",
            "body": [
                {
                    "data": {},
                    "content": [
                        {
                            "data": {},
                            "marks": [],
                            "value": "Senior internationals Chris Robshaw and Danny Care have been left out of England's first World Cup training squad.",
                            "nodeType": "text"
                        }
                    ],
                    "nodeType": "paragraph"
                },
                {
                    "data": {},
                    "content": [
                        {
                            "data": {},
                            "marks": [],
                            "value": "The Harlequins pair, with 150 caps between them, are not part of a 29-man group named by the Rugby Football Union.",
                            "nodeType": "text"
                        }
                    ],
                    "nodeType": "paragraph"
                },
                {
                    "data": {},
                    "content": [
                        {
                            "data": {},
                            "marks": [],
                            "value": "But four uncapped players are in the squad - Bath wing Ruaridh McConnochie, Gloucester's Georgia-born prop Val Rapava Ruskin, Northampton flanker Lewis Ludlam and Harlequins back-row forward Alex Dombrandt.",
                            "nodeType": "text"
                        }
                    ],
                    "nodeType": "paragraph"
                },
                {
                    "data": {},
                    "content": [
                        {
                            "data": {},
                            "marks": [],
                            "value": "Bristol-bound number eight Nathan Hughes also misses out, and whether another absentee - Northampton hooker Dylan Hartley - is called into camp at any point this summer remains to be seen.",
                            "nodeType": "text"
                        }
                    ],
                    "nodeType": "paragraph"
                },
                {
                    "data": {},
                    "content": [
                        {
                            "data": {},
                            "marks": [],
                            "value": "Hartley, who led England to Six Nations titles in 2016 and 2017, has not played for six months due to a knee problem and it is understood that he is still struggling with the issue.",
                            "nodeType": "text"
                        }
                    ],
                    "nodeType": "paragraph"
                },
                {
                    "data": {
                        "target": {
                            "sys": {
                                "space": {
                                    "sys": {
                                        "type": "Link",
                                        "linkType": "Space",
                                        "id": "j2hzbokj7ol2"
                                    }
                                },
                                "id": "3tjKIjZ4mt0CB4payWVq3u",
                                "type": "Asset",
                                "createdAt": "2019-06-20T13:18:47.613Z",
                                "updatedAt": "2019-06-20T13:18:47.613Z",
                                "environment": {
                                    "sys": {
                                        "id": "dev",
                                        "type": "Link",
                                        "linkType": "Environment"
                                    }
                                },
                                "revision": 1,
                                "locale": "en-GB"
                            },
                            "fields": {
                                "title": "Owen Farrel in-game England",
                                "file": {
                                    "url": "//images.ctfassets.net/j2hzbokj7ol2/3tjKIjZ4mt0CB4payWVq3u/e949b973c9db4189cb144c4333cc51c2/owen-farrel-in-game-england.jpg",
                                    "details": {
                                        "size": 44602,
                                        "image": {
                                            "width": 540,
                                            "height": 304
                                        }
                                    },
                                    "fileName": "owen-farrel-in-game-england.jpg",
                                    "contentType": "image/jpeg"
                                }
                            }
                        }
                    },
                    "content": [],
                    "nodeType": "embedded-asset-block"
                },
                {
                    "data": {},
                    "content": [
                        {
                            "data": {},
                            "marks": [],
                            "value": "Saracens fly-half Owen Farrell is an overwhelming favourite to captain England at the World Cup in Japan.",
                            "nodeType": "text"
                        }
                    ],
                    "nodeType": "paragraph"
                },
                {
                    "data": {},
                    "content": [
                        {
                            "data": {},
                            "marks": [],
                            "value": "Apart from Rapava Ruskin and Ludlam, players from clubs involved in the Gallagher Premiership semi-finals - Saracens, Exeter, Gloucester and Northampton - will not feature at this stage due to a mandatory five-week rest period.",
                            "nodeType": "text"
                        }
                    ],
                    "nodeType": "paragraph"
                },
                {
                    "data": {},
                    "content": [
                        {
                            "data": {},
                            "marks": [],
                            "value": "The pair, plus a small number involved for an England XV against the Barbarians on June 2, will be managed to ensure post-season active rest periods are fulfilled in agreement with Premiership Rugby and the Rugby Players' Association.",
                            "nodeType": "text"
                        }
                    ],
                    "nodeType": "paragraph"
                },
                {
                    "data": {},
                    "content": [
                        {
                            "data": {},
                            "marks": [],
                            "value": "Flanker Robshaw, 33, was England's 2015 World Cup captain, but he last featured for his country a year ago, and 32-year-old scrum-half Care did not gain selection during last season's Six Nations.",
                            "nodeType": "text"
                        }
                    ],
                    "nodeType": "paragraph"
                },
                {
                    "data": {},
                    "content": [
                        {
                            "data": {},
                            "marks": [],
                            "value": "The squad will assemble at Pennyhill Park in Surrey on Sunday for five days, before a second camp from June 30-July 4 when further Gloucester and Northampton players could be added.",
                            "nodeType": "text"
                        }
                    ],
                    "nodeType": "paragraph"
                },
                {
                    "data": {},
                    "content": [
                        {
                            "data": {},
                            "marks": [],
                            "value": "England boss Eddie Jones is due to name an official training squad on July 4, boosted by a potentially sizeable Saracens and Exeter contingent, before the first official World Cup camp begins three days later.",
                            "nodeType": "text"
                        }
                    ],
                    "nodeType": "paragraph"
                },
                {
                    "data": {},
                    "content": [
                        {
                            "data": {},
                            "marks": [],
                            "value": "Jones said: \"The first two England training camps are designed to improve individual players' fundamentals to allow them to compete for a place in the Rugby World Cup squad.\"",
                            "nodeType": "text"
                        }
                    ],
                    "nodeType": "paragraph"
                },
                {
                    "data": {},
                    "content": [
                        {
                            "data": {},
                            "marks": [],
                            "value": "Ruskin, 26, was born in Tbilisi, but moved to England at the age of two. He is a former Georgia Under-19 captain who played for Worcester before joining Gloucester.",
                            "nodeType": "text"
                        }
                    ],
                    "nodeType": "paragraph"
                },
                {
                    "data": {},
                    "content": [
                        {
                            "data": {},
                            "marks": [],
                            "value": "Former England Sevens star McConnochie enjoyed an outstanding debut season with Bath last term and Dombrandt, who was a colleague of Wales flanker Aaron Wainwright at college in Cardiff, and Ludlam have also maintained impressive club form.",
                            "nodeType": "text"
                        }
                    ],
                    "nodeType": "paragraph"
                },
                {
                    "data": {},
                    "content": [
                        {
                            "data": {},
                            "marks": [],
                            "value": "Saracens forwards Mako Vunipola and George Kruis, meanwhile, will attend the training camp for treatment.",
                            "nodeType": "text"
                        }
                    ],
                    "nodeType": "paragraph"
                },
                {
                    "data": {},
                    "content": [
                        {
                            "data": {},
                            "marks": [],
                            "value": "England's opening World Cup warm-up game is against Wales at Twickenham on August 11.",
                            "nodeType": "text"
                        }
                    ],
                    "nodeType": "paragraph"
                }
            ],
            "images": [
                {
                    "title": "Chris Robshaw England on-field portrait",
                    "file": {
                        "url": "//images.ctfassets.net/j2hzbokj7ol2/31zFNW2Ow6JU8sBHi3arnY/03118a3c4ddb4e3c92414b67ef30e4b7/chris-robshaw-england-on-field-portrait.png",
                        "details": {
                            "size": 806635,
                            "image": {
                                "width": 956,
                                "height": 716
                            }
                        },
                        "fileName": "chris-robshaw-england-on-field-portrait.png",
                        "contentType": "image/png"
                    }
                }
            ],
            "tags": [
                "Chris Robshaw",
                "Danny Care",
                "England"
            ]
        }
    ]
